{
    "shared":{
        "AppEntryWidth":  "200",
        "AppEntryFontSize":  "11",
        "AppEntryMargin":  "1,0,1,0",
        "AppEntryBorderThickness":  "0",
        "CustomDialogFontSize":       "12",
        "CustomDialogFontSizeHeader": "14",
        "CustomDialogLogoSize":       "25",
        "CustomDialogWidth":          "400",
        "CustomDialogHeight":         "200",
        "FontSize":         "12",
        "FontFamily":       "Arial",
        "HeaderFontSize":  "16",
        "HeaderFontFamily": "Consolas, Monaco",
        "CheckBoxBulletDecoratorSize": "14",
        "CheckBoxMargin": "15,0,0,2",
        "TabContentMargin":       "5",
        "TabButtonFontSize":      "14",
        "TabButtonWidth":         "110",
        "TabButtonHeight":        "28",
        "TabRowHeightInPixels":   "50",
        "ToolTipWidth":         "300",
        "IconFontSize":     "14",
        "IconButtonSize":   "35",
        "SettingsIconFontSize":   "18",
        "CloseIconFontSize":      "18",
        "GroupBorderBackgroundColor":  "#232629",
        "ButtonFontSize":   "12",
        "ButtonFontFamily": "Arial",
        "ButtonWidth":      "200",
        "ButtonHeight":     "28",
        "ConfigTabButtonFontSize":   "14",
        "ConfigUpdateButtonFontSize":   "14",
        "SearchBarWidth":               "200",
        "SearchBarHeight":              "26",
        "SearchBarTextBoxFontSize":     "12",
        "SearchBarClearButtonFontSize": "14",
        "CheckboxMouseOverColor": "#999999",
        "ButtonBorderThickness":  "1",
        "ButtonMargin":  "2",
        "ButtonCornerRadius": "8"
    },
    "Light": {
        "AppInstallUnselectedColor": "#F7F7F7",
        "AppInstallHighlightedColor": "#CFCFCF",
        "AppInstallSelectedColor": "#C2C2C2",
        "AppInstallOverlayBackgroundColor":"#6A6D72",
        "ComboBoxForegroundColor":  "#232629",
        "ComboBoxBackgroundColor":  "#F7F7F7",
        "LabelboxForegroundColor":  "#232629",
        "MainForegroundColor":  "#232629",
        "MainBackgroundColor":  "#F7F7F7",
        "LabelBackgroundColor":  "#F7F7F7",
        "LinkForegroundColor":  "#484848",
        "LinkHoverForegroundColor":  "#232629",
        "ScrollBarBackgroundColor": "#4A4D52",
        "ScrollBarHoverColor": "#5A5D62",
        "ScrollBarDraggingColor": "#6A6D72",

        "ProgressBarForegroundColor": "#2e77ff",
        "ProgressBarBackgroundColor": "Transparent",
        "ProgressBarTextColor": "#232629",
        "ButtonInstallBackgroundColor":  "#F7F7F7",
        "ButtonTweaksBackgroundColor":  "#F7F7F7",
        "ButtonConfigBackgroundColor":  "#F7F7F7",
        "ButtonUpdatesBackgroundColor":  "#F7F7F7",
        "ButtonWin11ISOBackgroundColor": "#F7F7F7",
        "ButtonInstallForegroundColor":  "#232629",
        "ButtonTweaksForegroundColor":  "#232629",
        "ButtonConfigForegroundColor":  "#232629",
        "ButtonUpdatesForegroundColor":  "#232629",
        "ButtonWin11ISOForegroundColor": "#232629",
        "ButtonBackgroundColor":  "#F5F5F5",
        "ButtonBackgroundPressedColor":  "#1A1A1A",
        "ButtonBackgroundMouseoverColor":  "#C2C2C2",
        "ButtonBackgroundSelectedColor":  "#F0F0F0",
        "ButtonForegroundColor":  "#232629",
        "ToggleButtonOnColor":  "#2e77ff",
        "ToggleButtonOffColor": "#707070",
        "ToolTipBackgroundColor": "#F7F7F7",
        "BorderColor": "#232629",
        "BorderOpacity": "0.2"

    },
    "Dark": {
    "AppInstallUnselectedColor": "#161D26",
    "AppInstallHighlightedColor": "#1C2733",
    "AppInstallSelectedColor": "#243444",
    "AppInstallOverlayBackgroundColor":"#0B1218",

    "ComboBoxForegroundColor":  "#EAF2F8",
    "ComboBoxBackgroundColor":  "#131B23",

    "LabelboxForegroundColor":  "#4CB3FF",
    "MainForegroundColor":  "#EAF2F8",
    "MainBackgroundColor":  "#0B1218",
    "LabelBackgroundColor":  "#0B1218",

    "LinkForegroundColor":  "#4CB3FF",
    "LinkHoverForegroundColor":  "#FFFFFF",

    "ScrollBarBackgroundColor": "#131B23",
    "ScrollBarHoverColor": "#1F2C39",
    "ScrollBarDraggingColor": "#4CB3FF",

    "ProgressBarForegroundColor": "#4CB3FF",
    "ProgressBarBackgroundColor": "Transparent",
    "ProgressBarTextColor": "#EAF2F8",

    "ButtonInstallBackgroundColor":  "#16212C",
    "ButtonTweaksBackgroundColor":  "#16212C",
    "ButtonConfigBackgroundColor":  "#16212C",
    "ButtonUpdatesBackgroundColor":  "#16212C",
    "ButtonWin11ISOBackgroundColor": "#16212C",

    "ButtonInstallForegroundColor":  "#EAF2F8",
    "ButtonTweaksForegroundColor":  "#EAF2F8",
    "ButtonConfigForegroundColor":  "#EAF2F8",
    "ButtonUpdatesForegroundColor":  "#EAF2F8",
    "ButtonWin11ISOForegroundColor": "#EAF2F8",

    "ButtonBackgroundColor":  "#16212C",
    "ButtonBackgroundPressedColor":  "#4CB3FF",
    "ButtonBackgroundMouseoverColor":  "#1F2C39",
    "ButtonBackgroundSelectedColor":  "#2B4660",
    "ButtonForegroundColor":  "#EAF2F8",

    "ToggleButtonOnColor": "#4CB3FF",
    "ToggleButtonOffColor": "#48545F",

    "ToolTipBackgroundColor": "#131B23",
    "BorderColor": "#233241",
    "BorderOpacity": "0.45"
}
}
